p600syx/__init__.py
p600syx/error.py
p600syx/gligli_sysex_parser.py
p600syx/sequential_sysex_parser.py
p600syx/sysex_parser.py
p600syx/util.py
p600syx-0.3.2.data/scripts/p600_decode
p600syx-0.3.2.data/scripts/p600_recv
p600syx-0.3.2.data/scripts/p600_send
p600syx-0.3.2.dist-info/LICENSE
p600syx-0.3.2.dist-info/METADATA
p600syx-0.3.2.dist-info/WHEEL
p600syx-0.3.2.dist-info/top_level.txt
p600syx-0.3.2.dist-info/RECORD
