Metadata-Version: 2.1
Name: p600syx
Version: 0.3.2
Summary: Python module for handling MIDI SysEx dumps from the Sequential Circuits Prophet-600 analog synthesizer.
Home-page: https://github.com/jmechnich/p600syx
Author: Joerg Mechnich
Author-email: joerg.mechnich@gmail.com
License: GNU GPLv3
Classifier: Programming Language :: Python :: 3
Classifier: License :: OSI Approved :: GNU General Public License v3 (GPLv3)
Classifier: Operating System :: POSIX :: Linux
Requires-Python: >=3.8
License-File: LICENSE
Requires-Dist: appdirs
Requires-Dist: mido
Requires-Dist: progress
Requires-Dist: python-rtmidi
